{
  "version": "curator-decision.v1",
  "article_id": "art-2026-03-01-020",
  "decision": "discarded",
  "qualified_by": "none",
  "evidence_basis": "mixed",
  "novelty_strength": "medium",
  "excerpt_sufficiency": "partial",
  "reason": "The provided excerpt only contains the README and Code of Conduct, offering no substantive research value, experimental data, or synthesis of findings. It does not meet any of the criteria for inclusion.",
  "limits": "This decision is based solely on the minimal content provided in the excerpt.",
  "confidence": "medium",
  "generated_at_utc": "2026-04-01T19:51:32Z",
  "mode": "agent"
}
